LICENSE
MANIFEST.in
README.txt
setup.py
dj_vga_w1.egg-info/PKG-INFO
dj_vga_w1.egg-info/SOURCES.txt
dj_vga_w1.egg-info/dependency_links.txt
dj_vga_w1.egg-info/requires.txt
dj_vga_w1.egg-info/top_level.txt
dpl1_main/__init__.py
dpl1_main/default.sqlite3
dpl1_main/deployment_util.py
dpl1_main/manage.py
dpl1_main/vwhdb.sqlite3
dpl1_main/DPL1/__init__.py
dpl1_main/DPL1/settings.py
dpl1_main/DPL1/urls.py
dpl1_main/DPL1/wsgi.py
dpl1_main/testing_app/__init__.py
dpl1_main/testing_app/admin.py
dpl1_main/testing_app/forms.py
dpl1_main/testing_app/models.py
dpl1_main/testing_app/session_util.py
dpl1_main/testing_app/tests.py
dpl1_main/testing_app/url_util.py
dpl1_main/testing_app/urls.py
dpl1_main/testing_app/view_util.py
dpl1_main/testing_app/views.py
dpl1_main/testing_app/fixtures/initial_data.json
dpl1_main/testing_app/static/testing_app/admin/css/base.css
dpl1_main/testing_app/static/testing_app/admin/css/ie.css
dpl1_main/testing_app/static/testing_app/admin/css/login.css
dpl1_main/testing_app/static/testing_app/admin/css/rtl.css
dpl1_main/testing_app/static/testing_app/admin/img/changelist-bg.gif
dpl1_main/testing_app/static/testing_app/admin/img/changelist-bg_rtl.gif
dpl1_main/testing_app/static/testing_app/admin/img/chooser-bg.gif
dpl1_main/testing_app/static/testing_app/admin/img/chooser_stacked-bg.gif
dpl1_main/testing_app/static/testing_app/admin/img/default-bg-reverse.gif
dpl1_main/testing_app/static/testing_app/admin/img/default-bg.gif
dpl1_main/testing_app/static/testing_app/admin/img/deleted-overlay.gif
dpl1_main/testing_app/static/testing_app/admin/img/icon-no.gif
dpl1_main/testing_app/static/testing_app/admin/img/icon-unknown.gif
dpl1_main/testing_app/static/testing_app/admin/img/icon-yes.gif
dpl1_main/testing_app/static/testing_app/admin/img/icon_addlink.gif
dpl1_main/testing_app/static/testing_app/admin/img/icon_alert.gif
dpl1_main/testing_app/static/testing_app/admin/img/icon_calendar.gif
dpl1_main/testing_app/static/testing_app/admin/img/icon_changelink.gif
dpl1_main/testing_app/static/testing_app/admin/img/icon_clock.gif
dpl1_main/testing_app/static/testing_app/admin/img/icon_deletelink.gif
