Metadata-Version: 1.1
Name: dj-vga-w1
Version: 0.0.22
Summary: The Django learning program project - a site where the usescan take tests, and the admins can maintain configurationsfor these tests
Home-page: https://github.com/vladiibine/dlp-assignment1
Author: Ardelean Vlad
Author-email: vlad.ardelean@3pillarglobal.com
License: UNKNOWN
Keywords: example tutorial django
Platform: UNKNOWN
Classifier: Development Status :: 1 - Planning
Classifier: Environment :: Web Environment
Classifier: Framework :: Django
Classifier: Intended Audience :: Developers
Classifier: License :: Free For Educational Use
